pathlib_cli/__init__.py
pathlib_cli/__main__.py
pathlib_cli-0.1.2.dist-info/METADATA
pathlib_cli-0.1.2.dist-info/WHEEL
pathlib_cli-0.1.2.dist-info/entry_points.txt
pathlib_cli-0.1.2.dist-info/RECORD
